pywkhtmltopdf/__init__.py
pywkhtmltopdf/tests/__init__.py
pywkhtmltopdf/tests/utils.py
pywkhtmltopdf-0.1.3.dist-info/DESCRIPTION.rst
pywkhtmltopdf-0.1.3.dist-info/METADATA
pywkhtmltopdf-0.1.3.dist-info/RECORD
pywkhtmltopdf-0.1.3.dist-info/WHEEL
pywkhtmltopdf-0.1.3.dist-info/metadata.json
pywkhtmltopdf-0.1.3.dist-info/top_level.txt
